drakpdb-0.2.2.dist-info/WHEEL
drakpdb-0.2.2.dist-info/entry_points.txt
drakpdb-0.2.2.dist-info/LICENSE
drakpdb-0.2.2.dist-info/top_level.txt
drakpdb-0.2.2.dist-info/RECORD
drakpdb-0.2.2.dist-info/METADATA
drakpdb/type_info.py
drakpdb/fetch_pdb.py
drakpdb/drakpdb.py
drakpdb/__main__.py
drakpdb/main.py
drakpdb/__init__.py
drakpdb/pdbparse/dbi.py
drakpdb/pdbparse/postfix_eval.py
drakpdb/pdbparse/symlookup.py
drakpdb/pdbparse/fpo.py
drakpdb/pdbparse/undname.py
drakpdb/pdbparse/info.py
drakpdb/pdbparse/pe.py
drakpdb/pdbparse/peinfo.py
drakpdb/pdbparse/_undname.cpython-311-x86_64-linux-gnu.so
drakpdb/pdbparse/undecorate.py
drakpdb/pdbparse/omap.py
drakpdb/pdbparse/gdata.py
drakpdb/pdbparse/dbgold.py
drakpdb/pdbparse/pdbparse.py
drakpdb/pdbparse/tpi.py
drakpdb/pdbparse/__init__.py
drakpdb/pdbparse/_undname/undname_py.c
drakpdb/pdbparse/_undname/undname.c
