Metadata-Version: 2.1
Name: drakpdb
Version: 0.2.2
Summary: Helper library to generate DRAKVUF profiles.
Classifier: License :: OSI Approved :: GNU General Public License v2 (GPLv2)
Classifier: Programming Language :: Python :: 3
Requires-Python: >=3.8
License-File: LICENSE
Requires-Dist: pefile>=2019.4.18
Requires-Dist: construct<3.0
Requires-Dist: requests
Requires-Dist: tqdm
